Metadata-Version: 2.1
Name: f5-common-sdk
Version: 3.0.22
Summary: F5 Networks Python SDK fork with improvements
Home-page: https://github.com/Blackwoodseller/f5-common-sdk
Author: F5 Networks
Author-email: anpawspro@gmail.com
License: Apache License, Version 2.0
Keywords: F5,sdk,api,icontrol,bigip,api,ltm
Platform: UNKNOWN
Classifier: Development Status :: 5 - Production/Stable
Classifier: License :: OSI Approved :: Apache Software License
Classifier: Operating System :: OS Independent
Classifier: Programming Language :: Python
Classifier: Intended Audience :: System Administrators
Requires-Dist: six (>=1.9.0)
Requires-Dist: six (<2.0.0)
Requires-Dist: f5-icontrol-rest (>=1.3.13)
Requires-Dist: f5-icontrol-rest (<2.0.0)
